HGSpy/__init__.py
HGSpy/cr.py
HGSpy/definitions.py
HGSpy/hgs.py
HGSpy/hgs_Tp.py
HGSpy/hgs_eq.py
HGSpy/hgs_find.py
HGSpy/hgs_id.py
HGSpy/hgs_isentropic.py
HGSpy/hgs_mixture.py
HGSpy/hgs_nozzle.py
HGSpy/hgs_print.py
HGSpy/hgs_prop.py
HGSpy/hgs_secant.py
HGSpy/hgs_solver.py
HGSpy/utils.py
HGSpy/data/DATA_7_coef.txt
HGSpy/data/__init__.py
HGSpy/data/data.hgs
HGSpy/data/downloader.py
HGSpy-1.1.dist-info/LICENSE
HGSpy-1.1.dist-info/METADATA
HGSpy-1.1.dist-info/WHEEL
HGSpy-1.1.dist-info/top_level.txt
HGSpy-1.1.dist-info/RECORD
