Metadata-Version: 2.1
Name: HGSpy
Version: 1.1
Summary: HGS chemical equation solver for python
Home-page: https://github.com/CalebFuster/HGSpy
Author: Caleb Fuster, Arnau Miro, Manel Soria
Author-email: Caleb Fuster <calebfuji@gmail.com>, Arnau Miro <arnau.miro@upc.edu>, Manel Soria <manel.soria@upc.edu>
Maintainer: Arnau Miro
Maintainer-email: Arnau Miro <arnau.miro@upc.edu>
License: GNU GENERAL PUBLIC LICENSE
Project-URL: Homepage, https://github.com/ManelSoria/HGSpy
Project-URL: Bug Reports, https://github.com/ManelSoria/HGSpy/issues
Project-URL: Source, https://github.com/ManelSoria/HGSpy
Keywords: HGS,Chemical equation,solver
Classifier: Development Status :: 5 - Production/Stable
Classifier: Intended Audience :: Science/Research
Classifier: Topic :: Scientific/Engineering
Classifier: License :: OSI Approved :: GNU General Public License v3 (GPLv3)
Classifier: Programming Language :: Python :: 3
Classifier: Programming Language :: Python :: 3.7
Classifier: Programming Language :: Python :: 3.8
Classifier: Programming Language :: Python :: 3.9
Classifier: Programming Language :: Python :: 3.10
Classifier: Programming Language :: Python :: 3.11
Classifier: Programming Language :: Python :: 3 :: Only
Requires-Python: >=3.7
License-File: LICENSE
Requires-Dist: numpy >=1.21.6
Requires-Dist: scipy >=1.5.4
Requires-Dist: matplotlib
Provides-Extra: full
